bplib/__init__.py
bplib/_bplib.abi3.so
bplib/bindings.py
bplib/bp.py
bplib/compile.py
bplib/pack.py
bplib/src/bp_fp12.c
bplib/src/bp_fp2.c
bplib/src/bp_fp6.c
bplib/src/bp_g1.c
bplib/src/bp_g2.c
bplib/src/bp_g2_mult.c
bplib/src/bp_group.c
bplib/src/bp_gt.c
bplib/src/bp_map.c
bplib_fork-0.0.63.dist-info/METADATA
bplib_fork-0.0.63.dist-info/WHEEL
bplib_fork-0.0.63.dist-info/top_level.txt
bplib_fork-0.0.63.dist-info/RECORD
