Metadata-Version: 2.1
Name: bplib-fork
Version: 0.0.63
Summary: A bilinear pairing library for petlib.
Home-page: https://pypi.python.org/pypi/bplib/
Author: George Danezis
Author-email: g.danezis@ucl.ac.uk
License: LGPL
Requires-Dist: cffi (>=1.0.0)
Requires-Dist: pycparser (>=2.10)
Requires-Dist: future (>=0.14.3)
Requires-Dist: pytest (>=2.5.0)
Requires-Dist: pytest-cov (>=1.8.1)
Requires-Dist: msgpack-python (>=0.4.6)
Requires-Dist: petlib-fork (>=0.0.43)
